{
  "recordings": [
    {
      "orderId": "nj_order_id",
      "skuId": "nj_sku_id",
      "date": "2025-11-22",
      "timestamp": 1763848101168,
      "storageType": "storj",
      "path": "nj_order_id/nj_sku_id/2025-11-22/recording_1763848101168.webm",
      "url": "https://gateway.storjshare.io/return-tracker/nj_order_id/nj_sku_id/2025-11-22/recording_1763848101168.webm",
      "filename": "recording_1763848101168.webm",
      "mimeType": "video/webm;codecs=vp9"
    },
    {
      "orderId": "asdf",
      "skuId": "asdf",
      "date": "2025-11-22",
      "timestamp": 1763848071243,
      "storageType": "storj",
      "path": "asdf/asdf/2025-11-22/recording_1763848071243.webm",
      "url": "https://gateway.storjshare.io/return-tracker/asdf/asdf/2025-11-22/recording_1763848071243.webm",
      "filename": "recording_1763848071243.webm",
      "mimeType": "video/webm;codecs=vp9"
    },
    {
      "orderId": "asdf",
      "skuId": "sadf",
      "date": "2025-11-22",
      "timestamp": 1763846424747,
      "storageType": "storj",
      "path": "asdf/sadf/2025-11-22/recording_1763846424747.webm",
      "url": "https://gateway.storjshare.io/return-tracker/asdf/sadf/2025-11-22/recording_1763846424747.webm",
      "filename": "recording_1763846424747.webm",
      "mimeType": "video/webm;codecs=vp9"
    },
    {
      "orderId": "nitesh order",
      "skuId": "nitesh sku",
      "date": "2025-11-22",
      "timestamp": 1763846153782,
      "storageType": "storj",
      "path": "2025-11-22/nitesh order/nitesh sku/recording_1763846153782.webm",
      "url": "https://gateway.storjshare.io/return-tracker/2025-11-22/nitesh order/nitesh sku/recording_1763846153782.webm",
      "filename": "recording_1763846153782.webm",
      "mimeType": "video/webm;codecs=vp9"
    },
    {
      "orderId": "nitesh",
      "skuId": "nitesh",
      "date": "2025-11-22",
      "timestamp": 1763846065420,
      "storageType": "storj",
      "path": "2025-11-22/nitesh/nitesh/recording_1763846065420.webm",
      "url": "https://gateway.storjshare.io/return-tracker/2025-11-22/nitesh/nitesh/recording_1763846065420.webm",
      "filename": "recording_1763846065420.webm",
      "mimeType": "video/webm;codecs=vp9"
    },
    {
      "orderId": "asdf",
      "skuId": "asdf",
      "date": "2025-11-22",
      "timestamp": 1763846038623,
      "storageType": "storj",
      "path": "2025-11-22/asdf/asdf/recording_1763846038623.webm",
      "url": "https://gateway.storjshare.io/return-tracker/2025-11-22/asdf/asdf/recording_1763846038623.webm",
      "filename": "recording_1763846038623.webm",
      "mimeType": "video/webm;codecs=vp9"
    },
    {
      "orderId": "milind",
      "skuId": "kate",
      "date": "2025-11-22",
      "timestamp": 1763844549586,
      "storageType": "storj",
      "path": "2025-11-22/milind/kate/recording_1763844549586.webm",
      "url": "https://gateway.storjshare.io/return-tracker/2025-11-22/milind/kate/recording_1763844549586.webm",
      "filename": "recording_1763844549586.webm",
      "mimeType": "video/webm;codecs=vp9"
    },
    {
      "orderId": "hey",
      "skuId": "testing",
      "date": "2025-11-22",
      "timestamp": 1763843430846,
      "storageType": "storj",
      "path": "2025-11-22/hey/testing/recording_1763843430846.webm",
      "url": "https://gateway.storjshare.io/return-tracker/2025-11-22/hey/testing/recording_1763843430846.webm",
      "filename": "recording_1763843430846.webm",
      "mimeType": "video/webm;codecs=vp9"
    },
    {
      "orderId": "test",
      "skuId": "testt",
      "date": "2025-11-22",
      "timestamp": 1763842971242,
      "storageType": "storj",
      "path": "2025-11-22/test/testt/recording_1763842971242.webm",
      "url": "https://gateway.storjshare.io/return-tracker/2025-11-22/test/testt/recording_1763842971242.webm",
      "filename": "recording_1763842971242.webm",
      "mimeType": "video/webm;codecs=vp9"
    }
  ],
  "lastUpdated": 1763848102512
}